superelasticsearch
