Metadata-Version: 1.1
Name: superelasticsearch
Version: 0.1.1
Summary: An extended version of the official Elasticsearch Python client.
Home-page: UNKNOWN
Author: Wingify Engineering
Author-email: dev@wingify.com
License: UNKNOWN
Platform: UNKNOWN
Classifier: Development Status :: 2 - Pre-Alpha
Classifier: Intended Audience :: Developers
Classifier: Operating System :: OS Independent
Classifier: Programming Language :: Python
